rmapy/__init__.py
rmapy/api.py
rmapy/collections.py
rmapy/config.py
rmapy/const.py
rmapy/document.py
rmapy/exceptions.py
rmapy/folder.py
rmapy/meta.py
rmapy/types.py
rmapy-0.3.1.dist-info/LICENSE.txt
rmapy-0.3.1.dist-info/METADATA
rmapy-0.3.1.dist-info/WHEEL
rmapy-0.3.1.dist-info/top_level.txt
rmapy-0.3.1.dist-info/RECORD
